midstar/__init__.py
midstar/core/__init__.py
midstar/core/backend.py
midstar/core/types.py
midstar/middleware/__init__.py
midstar/middleware/cache.py
midstar/middleware/compress.py
midstar/middleware/concurrent.py
midstar/middleware/csrf.py
midstar/middleware/error_handle.py
midstar/middleware/http2_push.py
midstar/middleware/jwt.py
midstar/middleware/rate_limit.py
midstar/middleware/security_header.py
midstar-0.2.0.dist-info/LICENSE
midstar-0.2.0.dist-info/METADATA
midstar-0.2.0.dist-info/WHEEL
midstar-0.2.0.dist-info/RECORD
